{
    "package": "me.jellysquid.mods.lithium.mixin",
    "required": true,
    "compatibilityLevel": "JAVA_8",
    "plugin": "me.jellysquid.mods.lithium.mixin.LithiumMixinPlugin",
    "injectors": {
        "defaultRequire": 1
    },
    "client": [
        "ai.nearby_entity_tracking.MixinClientWorld",
        "client.fast_loading_screen.MixinLevelLoadingScreen"
    ],
    "mixins": [
        "ai.goal.MixinGoal",
        "ai.goal.MixinGoalSelector",
        "ai.nearby_entity_tracking.MixinLivingEntity",
        "ai.nearby_entity_tracking.MixinServerWorld",
        "ai.nearby_entity_tracking.MixinWorld",
        "ai.nearby_entity_tracking.goals.MixinFleeEntityGoal",
        "ai.nearby_entity_tracking.goals.MixinLookAtGoal",
        "ai.raid.MixinPickupBannerAsLeaderGoal",
        "ai.raid.MixinRaid",
        "ai.task.MixinCompositeTask",
        "ai.task.MixinFindInteractionTargetTask",
        "ai.task.MixinRunMode",
        "ai.task.MixinTask",
        "ai.task.MixinWeightedList",
        "avoid_allocations.MixinServerWorld",
        "avoid_allocations.MixinWorld",
        "avoid_allocations.enum_values.MixinLivingEntity",
        "avoid_allocations.enum_values.MixinPistonBlock",
        "avoid_allocations.enum_values.MixinPistonHandler",
        "avoid_allocations.enum_values.MixinServerChunkManager",
        "biome.MixinVoronoiBiomeAccessType",
        "block.block_state_cache.MixinAbstractBlockState",
        "block.piston_shapes.MixinPistonHeadBlock",
        "cached_hashcode.MixinBlockNeighborGroup",
        "chunk.no_locking.MixinPalettedContainer",
        "chunk.palette.MixinPalettedContainer",
        "chunk.serialization.MixinPackedIntegerArray",
        "chunk.serialization.MixinPalettedContainer",
        "collections.entity_filtering.MixinTypeFilterableList",
        "entity.block_cache.MixinLivingEntity",
        "entity.collisions.MixinCollisionView",
        "entity.collisions.MixinEntity",
        "entity.collisions.MixinEntityView",
        "entity.data_tracker.no_locks.MixinDataTracker",
        "entity.data_tracker.use_arrays.MixinDataTracker",
        "entity.fluid_checks.MixinEntity",
        "math.fast_util.MixinAxisCycleDirection",
        "math.fast_util.MixinBox",
        "math.fast_util.MixinDirection",
        "poi.fast_init.MixinPointOfInterestStorage",
        "poi.fast_init.MixinPointOfInterestType",
        "poi.fast_retrieval.MixinPointOfInterestSet",
        "poi.fast_retrieval.MixinPointOfInterestStorage",
        "poi.fast_retrieval.MixinSerializingRegionBasedStorage",
        "redstone.MixinRedstoneWireBlock",
        "redstone.MixinWorld",
        "shapes.blockstate_cache.MixinAbstractBlockState",
        "shapes.blockstate_cache.MixinBlock",
        "shapes.blockstate_cache.MixinBlockShapeCache",
        "shapes.precompute_shape_arrays.MixinSimpleVoxelShape",
        "shapes.shape_merging.MixinVoxelShapes",
        "shapes.specialized_shapes.MixinVoxelShape",
        "shapes.specialized_shapes.MixinVoxelShapes",
        "tag.MixinTag",
        "world.chunk_task_system.MixinChunkTaskPrioritySystem",
        "world.chunk_tickets.MixinChunkTicket",
        "world.chunk_tickets.MixinSortedArraySet",
        "world.chunk_ticking.MixinPlayerChunkWatchingManager",
        "world.chunk_ticking.MixinThreadedAnvilChunkStorage",
        "world.explosions.MixinExplosion",
        "world.fire_checks.MixinWorld",
        "world.region_sync.MixinRegionBasedStorage",
        "world.region_sync.MixinRegionFile",
        "world.region_sync.MixinServerWorld",
        "world.region_sync.MixinStorageIoWorker",
        "world.region_sync.MixinThreadedAnvilChunkStorage",
        "world.region_sync.MixinVersionedChunkStorage",
        "world.tick_scheduler.MixinServerWorld"
    ]
}